{"nodes": [{"id": "fillblankquestion", "label": "FillBlankQuestion.tsx", "file_type": "code", "source_file": "WorkSpace_Alpha\\src\\components\\fillBlank\\FillBlankQuestion.tsx", "source_location": "L1"}, {"id": "fillblankquestion_fillblankquestion", "label": "FillBlankQuestion()", "file_type": "code", "source_file": "WorkSpace_Alpha\\src\\components\\fillBlank\\FillBlankQuestion.tsx", "source_location": "L17"}], "edges": [{"source": "fillblankquestion", "target": "react", "relation": "imports_from", "confidence": "EXTRACTED", "source_file": "WorkSpace_Alpha\\src\\components\\fillBlank\\FillBlankQuestion.tsx", "source_location": "L3", "weight": 1.0}, {"source": "fillblankquestion", "target": "framer_motion", "relation": "imports_from", "confidence": "EXTRACTED", "source_file": "WorkSpace_Alpha\\src\\components\\fillBlank\\FillBlankQuestion.tsx", "source_location": "L4", "weight": 1.0}, {"source": "fillblankquestion", "target": "lucide_react", "relation": "imports_from", "confidence": "EXTRACTED", "source_file": "WorkSpace_Alpha\\src\\components\\fillBlank\\FillBlankQuestion.tsx", "source_location": "L5", "weight": 1.0}, {"source": "fillblankquestion", "target": "particleeffect", "relation": "imports_from", "confidence": "EXTRACTED", "source_file": "WorkSpace_Alpha\\src\\components\\fillBlank\\FillBlankQuestion.tsx", "source_location": "L6", "weight": 1.0}, {"source": "fillblankquestion", "target": "usesoundplayer", "relation": "imports_from", "confidence": "EXTRACTED", "source_file": "WorkSpace_Alpha\\src\\components\\fillBlank\\FillBlankQuestion.tsx", "source_location": "L7", "weight": 1.0}, {"source": "fillblankquestion", "target": "mockdata", "relation": "imports_from", "confidence": "EXTRACTED", "source_file": "WorkSpace_Alpha\\src\\components\\fillBlank\\FillBlankQuestion.tsx", "source_location": "L8", "weight": 1.0}, {"source": "fillblankquestion", "target": "fillblankquestion_fillblankquestion", "relation": "contains", "confidence": "EXTRACTED", "source_file": "WorkSpace_Alpha\\src\\components\\fillBlank\\FillBlankQuestion.tsx", "source_location": "L17", "weight": 1.0}]}